object_serializer/__init__.py
object_serializer/serializer_factory.py
object_serializer/serializer_proxy.py
object_serializer/built_in_serializers/__init__.py
object_serializer/built_in_serializers/base.py
object_serializer/built_in_serializers/json_serializer.py
object_serializer/built_in_serializers/xml_serializer.py
object_serializer/pre_serializer/__init__.py
object_serializer/pre_serializer/tool.py
object_serializer/pre_serializer/utils.py
dempasha_serializer_v2-0.0.1.dist-info/METADATA
dempasha_serializer_v2-0.0.1.dist-info/WHEEL
dempasha_serializer_v2-0.0.1.dist-info/top_level.txt
dempasha_serializer_v2-0.0.1.dist-info/RECORD
