Metadata-Version: 2.1
Name: dempasha-serializer-v2
Version: 0.0.1
Summary: Serialzation tool
Home-page: UNKNOWN
Author: Pavel Demeshkevich
Author-email: <mail@neuralnine.com>
License: UNKNOWN
Keywords: python,serializer
Platform: UNKNOWN
Classifier: Development Status :: 1 - Planning
Classifier: Intended Audience :: Developers
Classifier: Programming Language :: Python :: 3
Classifier: Operating System :: Unix
Classifier: Operating System :: MacOS :: MacOS X
Classifier: Operating System :: Microsoft :: Windows
